{
    "scifact": [
        {
            "gamma": 0.0,
            "ndcg@10": 0.646584567652581,
            "mrr@10": 0.6257460317460317
        },
        {
            "gamma": 0.001,
            "ndcg@10": 0.646584567652581,
            "mrr@10": 0.6257460317460317
        },
        {
            "gamma": 0.005,
            "ndcg@10": 0.639491860346445,
            "mrr@10": 0.6160238095238095
        },
        {
            "gamma": 0.01,
            "ndcg@10": 0.6324456806601525,
            "mrr@10": 0.6070238095238095
        },
        {
            "gamma": 0.05,
            "ndcg@10": 0.6521696486722653,
            "mrr@10": 0.635079365079365
        },
        {
            "gamma": 0.1,
            "ndcg@10": 0.6308562496344234,
            "mrr@10": 0.6107222222222223
        },
        {
            "gamma": 0.2,
            "ndcg@10": 0.5852912001957621,
            "mrr@10": 0.5712222222222222
        },
        {
            "gamma": 0.5,
            "ndcg@10": 0.5074602362591542,
            "mrr@10": 0.48816666666666664
        },
        {
            "gamma": 1.0,
            "ndcg@10": 0.422093747675858,
            "mrr@10": 0.3834126984126984
        }
    ],
    "nfcorpus": [
        {
            "gamma": 0.0,
            "ndcg@10": 0.3076916983776239,
            "mrr@10": 0.5990000000000001
        },
        {
            "gamma": 0.001,
            "ndcg@10": 0.30894745505866994,
            "mrr@10": 0.6016666666666667
        },
        {
            "gamma": 0.005,
            "ndcg@10": 0.30795743311142465,
            "mrr@10": 0.5891904761904762
        },
        {
            "gamma": 0.01,
            "ndcg@10": 0.30541883561052224,
            "mrr@10": 0.5713888888888888
        },
        {
            "gamma": 0.05,
            "ndcg@10": 0.26727889856050285,
            "mrr@10": 0.5071904761904762
        },
        {
            "gamma": 0.1,
            "ndcg@10": 0.24328812496072935,
            "mrr@10": 0.47771428571428565
        },
        {
            "gamma": 0.2,
            "ndcg@10": 0.22430779093869585,
            "mrr@10": 0.4706031746031746
        },
        {
            "gamma": 0.5,
            "ndcg@10": 0.16909206151358028,
            "mrr@10": 0.367468253968254
        },
        {
            "gamma": 1.0,
            "ndcg@10": 0.15596747067723543,
            "mrr@10": 0.3417777777777778
        }
    ],
    "scidocs": [
        {
            "gamma": 0.0,
            "ndcg@10": 0.12816108666462367,
            "mrr@10": 0.23204761904761906
        },
        {
            "gamma": 0.001,
            "ndcg@10": 0.1280398812768115,
            "mrr@10": 0.23169047619047622
        },
        {
            "gamma": 0.005,
            "ndcg@10": 0.13016493245515492,
            "mrr@10": 0.2406904761904762
        },
        {
            "gamma": 0.01,
            "ndcg@10": 0.12425923904173489,
            "mrr@10": 0.2325
        },
        {
            "gamma": 0.05,
            "ndcg@10": 0.11674474036091531,
            "mrr@10": 0.21054761904761904
        },
        {
            "gamma": 0.1,
            "ndcg@10": 0.1025949979820351,
            "mrr@10": 0.1874126984126984
        },
        {
            "gamma": 0.2,
            "ndcg@10": 0.09879537336177853,
            "mrr@10": 0.18371428571428566
        },
        {
            "gamma": 0.5,
            "ndcg@10": 0.08823866819968837,
            "mrr@10": 0.15935714285714284
        },
        {
            "gamma": 1.0,
            "ndcg@10": 0.07995910373358202,
            "mrr@10": 0.12896825396825395
        }
    ]
}